sunbeam/__init__.py
sunbeam/manifest.py
sunbeam/page.py
sunbeam-0.2.3.dist-info/LICENSE
sunbeam-0.2.3.dist-info/WHEEL
sunbeam-0.2.3.dist-info/METADATA
sunbeam-0.2.3.dist-info/RECORD
